README.md
setup.py
OrganisorAndLoginRequiredMixin/__init__.py
OrganisorAndLoginRequiredMixin/mixin.py
OrganisorAndLoginRequiredMixin.egg-info/PKG-INFO
OrganisorAndLoginRequiredMixin.egg-info/SOURCES.txt
OrganisorAndLoginRequiredMixin.egg-info/dependency_links.txt
OrganisorAndLoginRequiredMixin.egg-info/top_level.txt