Metadata-Version: 2.1
Name: OrganisorAndLoginRequiredMixin
Version: 1.0.0
Summary: This package is to implement customized login operations on Django Framework.
Author: Shayam Shah
Author-email: shayamshah1999@gmail.com
